mcp_ds_toolkit_server/__init__.py
mcp_ds_toolkit_server/__main__.py
mcp_ds_toolkit_server/exceptions.py
mcp_ds_toolkit_server/server.py
mcp_ds_toolkit_server/data/__init__.py
mcp_ds_toolkit_server/data/cleaning.py
mcp_ds_toolkit_server/data/loader.py
mcp_ds_toolkit_server/data/model_evaluation.py
mcp_ds_toolkit_server/data/preprocessing.py
mcp_ds_toolkit_server/data/profiling.py
mcp_ds_toolkit_server/data/splitting.py
mcp_ds_toolkit_server/data/validation.py
mcp_ds_toolkit_server/tools/__init__.py
mcp_ds_toolkit_server/tools/base.py
mcp_ds_toolkit_server/tools/data_management.py
mcp_ds_toolkit_server/tools/tracking_tools.py
mcp_ds_toolkit_server/tools/training_tools.py
mcp_ds_toolkit_server/tracking/__init__.py
mcp_ds_toolkit_server/tracking/local_tracking.py
mcp_ds_toolkit_server/training/__init__.py
mcp_ds_toolkit_server/training/evaluator.py
mcp_ds_toolkit_server/training/trainer.py
mcp_ds_toolkit_server/utils/__init__.py
mcp_ds_toolkit_server/utils/common.py
mcp_ds_toolkit_server/utils/config.py
mcp_ds_toolkit_server/utils/data_resolver.py
mcp_ds_toolkit_server/utils/logger.py
mcp_ds_toolkit_server/utils/model_resolver.py
mcp_ds_toolkit_server/utils/persistence.py
mcp_ds_toolkit_server-0.3.0.dist-info/METADATA
mcp_ds_toolkit_server-0.3.0.dist-info/WHEEL
mcp_ds_toolkit_server-0.3.0.dist-info/entry_points.txt
mcp_ds_toolkit_server-0.3.0.dist-info/licenses/LICENSE
mcp_ds_toolkit_server-0.3.0.dist-info/RECORD
