Metadata-Version: 2.4
Name: mcp-ds-toolkit-server
Version: 0.3.0
Summary: Pure standalone MCP Data Science Server - Complete DS workflows with local SQLite tracking, no external services required
Project-URL: Homepage, https://github.com/Yasserelhaddar/MCP-DS-Toolkit-Server
Project-URL: Repository, https://github.com/Yasserelhaddar/MCP-DS-Toolkit-Server
Project-URL: Bug Tracker, https://github.com/Yasserelhaddar/MCP-DS-Toolkit-Server/issues
Author-email: Yasser El Haddar <yasserelhaddar@gmail.com>
License: MIT
License-File: LICENSE
Keywords: data-science,local-tracking,machine-learning,mcp,scikit-learn,sqlite,standalone
Classifier: Development Status :: 3 - Alpha
Classifier: Intended Audience :: Developers
Classifier: Intended Audience :: Science/Research
Classifier: License :: OSI Approved :: MIT License
Classifier: Programming Language :: Python :: 3
Classifier: Programming Language :: Python :: 3.12
Classifier: Topic :: Scientific/Engineering :: Artificial Intelligence
Classifier: Topic :: Software Development :: Libraries :: Python Modules
Requires-Python: >=3.12
Requires-Dist: joblib>=1.3.0
Requires-Dist: matplotlib>=3.7.0
Requires-Dist: mcp>=1.0.0
Requires-Dist: numpy>=1.26.0
Requires-Dist: pandas>=2.2.0
Requires-Dist: pyyaml>=6.0.1
Requires-Dist: requests>=2.31.0
Requires-Dist: scikit-learn>=1.4.0
Requires-Dist: scipy>=1.11.0
Requires-Dist: seaborn>=0.13.2
Provides-Extra: all
Requires-Dist: azure-identity>=1.12.0; extra == 'all'
Requires-Dist: azure-storage-blob>=12.0.0; extra == 'all'
Requires-Dist: bandit>=1.7.0; extra == 'all'
Requires-Dist: black>=24.0.0; extra == 'all'
Requires-Dist: boto3>=1.28.0; extra == 'all'
Requires-Dist: flake8>=7.0.0; extra == 'all'
Requires-Dist: gcsfs>=2023.1.0; extra == 'all'
Requires-Dist: google-cloud-storage>=2.10.0; extra == 'all'
Requires-Dist: ipython>=8.21.0; extra == 'all'
Requires-Dist: isort>=5.13.0; extra == 'all'
Requires-Dist: jupyter>=1.0.0; extra == 'all'
Requires-Dist: mypy>=1.8.0; extra == 'all'
Requires-Dist: myst-parser>=2.0.0; extra == 'all'
Requires-Dist: notebook>=7.0.0; extra == 'all'
Requires-Dist: pip-audit>=2.6.0; extra == 'all'
Requires-Dist: pre-commit>=3.6.0; extra == 'all'
Requires-Dist: pytest-asyncio>=0.23.0; extra == 'all'
Requires-Dist: pytest-cov>=4.0.0; extra == 'all'
Requires-Dist: pytest-mock>=3.12.0; extra == 'all'
Requires-Dist: pytest-xdist>=3.5.0; extra == 'all'
Requires-Dist: pytest>=8.0.0; extra == 'all'
Requires-Dist: s3fs>=2023.1.0; extra == 'all'
Requires-Dist: safety>=2.3.0; extra == 'all'
Requires-Dist: sphinx-autodoc-typehints>=1.25.0; extra == 'all'
Requires-Dist: sphinx-rtd-theme>=2.0.0; extra == 'all'
Requires-Dist: sphinx>=7.2.0; extra == 'all'
Provides-Extra: aws
Requires-Dist: boto3>=1.28.0; extra == 'aws'
Requires-Dist: s3fs>=2023.1.0; extra == 'aws'
Provides-Extra: azure
Requires-Dist: azure-identity>=1.12.0; extra == 'azure'
Requires-Dist: azure-storage-blob>=12.0.0; extra == 'azure'
Provides-Extra: dev
Requires-Dist: bandit>=1.7.0; extra == 'dev'
Requires-Dist: black>=24.0.0; extra == 'dev'
Requires-Dist: flake8>=7.0.0; extra == 'dev'
Requires-Dist: ipython>=8.21.0; extra == 'dev'
Requires-Dist: isort>=5.13.0; extra == 'dev'
Requires-Dist: jupyter>=1.0.0; extra == 'dev'
Requires-Dist: mypy>=1.8.0; extra == 'dev'
Requires-Dist: notebook>=7.0.0; extra == 'dev'
Requires-Dist: pip-audit>=2.6.0; extra == 'dev'
Requires-Dist: pre-commit>=3.6.0; extra == 'dev'
Requires-Dist: pytest-asyncio>=0.23.0; extra == 'dev'
Requires-Dist: pytest-cov>=4.0.0; extra == 'dev'
Requires-Dist: pytest-mock>=3.12.0; extra == 'dev'
Requires-Dist: pytest-xdist>=3.5.0; extra == 'dev'
Requires-Dist: pytest>=8.0.0; extra == 'dev'
Requires-Dist: safety>=2.3.0; extra == 'dev'
Provides-Extra: docs
Requires-Dist: myst-parser>=2.0.0; extra == 'docs'
Requires-Dist: sphinx-autodoc-typehints>=1.25.0; extra == 'docs'
Requires-Dist: sphinx-rtd-theme>=2.0.0; extra == 'docs'
Requires-Dist: sphinx>=7.2.0; extra == 'docs'
Provides-Extra: gcp
Requires-Dist: gcsfs>=2023.1.0; extra == 'gcp'
Requires-Dist: google-cloud-storage>=2.10.0; extra == 'gcp'
